ebel/__init__.py
e_bel-1.0.dist-info/METADATA
e_bel-1.0.dist-info/WHEEL
e_bel-1.0.dist-info/top_level.txt
e_bel-1.0.dist-info/RECORD
