Metadata-Version: 2.1
Name: e-bel
Version: 1.0
Summary: Electric Belief - bayesian statistics for the people
Home-page: https://electricbelief.ai
Author: Electric Belief Admin
Author-email: mmebel1234@gmail.com
License: UNKNOWN
Platform: UNKNOWN
